quixstreams/__init__.py
quixstreams/app.py
quixstreams/context.py
quixstreams/error_callbacks.py
quixstreams/internal_producer.py
quixstreams/logging.py
quixstreams/py.typed
quixstreams/runtracker.py
quixstreams/types.py
quixstreams/checkpointing/__init__.py
quixstreams/checkpointing/checkpoint.py
quixstreams/checkpointing/exceptions.py
quixstreams/core/__init__.py
quixstreams/core/stream/__init__.py
quixstreams/core/stream/exceptions.py
quixstreams/core/stream/stream.py
quixstreams/core/stream/functions/__init__.py
quixstreams/core/stream/functions/apply.py
quixstreams/core/stream/functions/base.py
quixstreams/core/stream/functions/filter.py
quixstreams/core/stream/functions/transform.py
quixstreams/core/stream/functions/types.py
quixstreams/core/stream/functions/update.py
quixstreams/dataframe/__init__.py
quixstreams/dataframe/dataframe.py
quixstreams/dataframe/exceptions.py
quixstreams/dataframe/registry.py
quixstreams/dataframe/series.py
quixstreams/dataframe/utils.py
quixstreams/dataframe/joins/__init__.py
quixstreams/dataframe/joins/base.py
quixstreams/dataframe/joins/join_asof.py
quixstreams/dataframe/joins/join_interval.py
quixstreams/dataframe/joins/utils.py
quixstreams/dataframe/joins/lookups/__init__.py
quixstreams/dataframe/joins/lookups/base.py
quixstreams/dataframe/joins/lookups/postgresql.py
quixstreams/dataframe/joins/lookups/sqlite.py
quixstreams/dataframe/joins/lookups/utils.py
quixstreams/dataframe/joins/lookups/quix_configuration_service/__init__.py
quixstreams/dataframe/joins/lookups/quix_configuration_service/cache.py
quixstreams/dataframe/joins/lookups/quix_configuration_service/environment.py
quixstreams/dataframe/joins/lookups/quix_configuration_service/lookup.py
quixstreams/dataframe/joins/lookups/quix_configuration_service/models.py
quixstreams/dataframe/windows/__init__.py
quixstreams/dataframe/windows/aggregations.py
quixstreams/dataframe/windows/base.py
quixstreams/dataframe/windows/count_based.py
quixstreams-3.23.0.dist-info/LICENSE
quixstreams-3.23.0.dist-info/METADATA
quixstreams-3.23.0.dist-info/WHEEL
quixstreams-3.23.0.dist-info/top_level.txt
quixstreams-3.23.0.dist-info/RECORD
