Metadata-Version: 2.1
Name: quixstreams
Version: 3.23.0
Summary: Python library for building stream processing applications with Apache Kafka
Author-email: Quix Analytics Ltd <devs@quix.io>
License: Apache License
Project-URL: Homepage, https://github.com/quixio/quix-streams
Keywords: streaming,processing,pipeline,event,real-time,time series,DataFrame,Kafka,Quix
Classifier: Development Status :: 5 - Production/Stable
Classifier: Intended Audience :: Developers
Classifier: License :: OSI Approved :: Apache Software License
Classifier: Operating System :: Microsoft :: Windows
Classifier: Operating System :: POSIX :: Linux
Classifier: Operating System :: MacOS :: MacOS X
Classifier: Programming Language :: Python :: 3
Requires-Python: <4,>=3.9
License-File: LICENSE
Requires-Dist: confluent-kafka[avro,json,protobuf,schemaregistry] <2.12,>=2.8.2
Requires-Dist: rocksdict <0.4,>=0.3
Requires-Dist: typing-extensions >=4.8
Requires-Dist: orjson <4,>=3.9
Requires-Dist: pydantic <2.12,>=2.7
Requires-Dist: pydantic-settings <2.11,>=2.3
Requires-Dist: jsonschema >=4.3.0
Requires-Dist: jsonlines <5,>=4
Requires-Dist: rich <15,>=13
Requires-Dist: jsonpath-ng <2,>=1.7.0
Requires-Dist: httpx >=0.28.1
Provides-Extra: all
Requires-Dist: fastavro <2.0,>=1.8 ; extra == 'all'
Requires-Dist: protobuf <7.0,>=5.27.2 ; extra == 'all'
Requires-Dist: influxdb3-python[pandas] <1.0,>=0.7 ; extra == 'all'
Requires-Dist: pyiceberg[glue,pyarrow] >=0.7 ; extra == 'all'
Requires-Dist: google-cloud-bigquery <3.27,>=3.26.0 ; extra == 'all'
Requires-Dist: google-cloud-pubsub <3,>=2.23.1 ; extra == 'all'
Requires-Dist: psycopg2-binary <3,>=2.9.9 ; extra == 'all'
Requires-Dist: boto3 <2.0,>=1.35.65 ; extra == 'all'
Requires-Dist: boto3-stubs <2.0,>=1.35.65 ; extra == 'all'
Requires-Dist: mypy-boto3-kinesis <2.0,>=1.35.65 ; extra == 'all'
Requires-Dist: mypy-boto3-s3 <2.0,>=1.35.65 ; extra == 'all'
Requires-Dist: redis[hiredis] <6,>=5.2.0 ; extra == 'all'
Requires-Dist: azure-storage-blob <12.25,>=12.24.0 ; extra == 'all'
Requires-Dist: neo4j <6,>=5.27.0 ; extra == 'all'
Requires-Dist: pymongo <5,>=4.11 ; extra == 'all'
Requires-Dist: pandas <3.0,>=1.0.0 ; extra == 'all'
Requires-Dist: elasticsearch <9,>=8.17 ; extra == 'all'
Requires-Dist: influxdb <6,>=5.3 ; extra == 'all'
Requires-Dist: python-dateutil <3,>=2.8.2 ; extra == 'all'
Requires-Dist: paho-mqtt <3,>=2.1.0 ; extra == 'all'
Provides-Extra: avro
Requires-Dist: fastavro <2.0,>=1.8 ; extra == 'avro'
Provides-Extra: aws
Requires-Dist: boto3 <2.0,>=1.35.65 ; extra == 'aws'
Requires-Dist: boto3-stubs <2.0,>=1.35.65 ; extra == 'aws'
Provides-Extra: azure
Requires-Dist: azure-storage-blob <12.25,>=12.24.0 ; extra == 'azure'
Provides-Extra: azure-file
Requires-Dist: quixstreams[azure] ; extra == 'azure-file'
Provides-Extra: bigquery
Requires-Dist: google-cloud-bigquery <3.27,>=3.26.0 ; extra == 'bigquery'
Provides-Extra: elasticsearch
Requires-Dist: elasticsearch <9,>=8.17 ; extra == 'elasticsearch'
Provides-Extra: iceberg
Requires-Dist: pyiceberg[pyarrow] >=0.7 ; extra == 'iceberg'
Provides-Extra: iceberg_aws
Requires-Dist: pyiceberg[glue,pyarrow] >=0.7 ; extra == 'iceberg_aws'
Provides-Extra: influxdb1
Requires-Dist: influxdb <6,>=5.3 ; extra == 'influxdb1'
Provides-Extra: influxdb3
Requires-Dist: influxdb3-python[pandas] <1.0,>=0.7 ; extra == 'influxdb3'
Provides-Extra: kinesis
Requires-Dist: quixstreams[aws] ; extra == 'kinesis'
Requires-Dist: mypy-boto3-kinesis <2.0,>=1.35.65 ; extra == 'kinesis'
Provides-Extra: mongodb
Requires-Dist: pymongo <5,>=4.11 ; extra == 'mongodb'
Provides-Extra: mqtt
Requires-Dist: paho-mqtt <3,>=2.1.0 ; extra == 'mqtt'
Provides-Extra: neo4j
Requires-Dist: neo4j <6,>=5.27.0 ; extra == 'neo4j'
Provides-Extra: pandas
Requires-Dist: pandas <3.0,>=1.0.0 ; extra == 'pandas'
Provides-Extra: parquet
Requires-Dist: pyarrow >=17.0.0 ; extra == 'parquet'
Provides-Extra: postgresql
Requires-Dist: psycopg2-binary <3,>=2.9.9 ; extra == 'postgresql'
Requires-Dist: types-psycopg2 <3,>=2.9 ; extra == 'postgresql'
Provides-Extra: protobuf
Requires-Dist: protobuf <7.0,>=5.27.2 ; extra == 'protobuf'
Provides-Extra: pubsub
Requires-Dist: google-cloud-pubsub <3,>=2.23.1 ; extra == 'pubsub'
Provides-Extra: redis
Requires-Dist: redis[hiredis] <6,>=5.2.0 ; extra == 'redis'
Provides-Extra: s3
Requires-Dist: quixstreams[aws] ; extra == 's3'
Requires-Dist: mypy-boto3-s3 <2.0,>=1.35.65 ; extra == 's3'
Provides-Extra: tdengine
Requires-Dist: python-dateutil <3,>=2.8.2 ; extra == 'tdengine'
